langchain_aisearchapi/__init__.py
langchain_aisearchapi/core.py
langchain_aisearchapi/py.typed
langchain_aisearchapi-1.0.5.dist-info/METADATA
langchain_aisearchapi-1.0.5.dist-info/WHEEL
langchain_aisearchapi-1.0.5.dist-info/licenses/LICENSE
langchain_aisearchapi-1.0.5.dist-info/RECORD
