Metadata-Version: 2.4
Name: langchain-aisearchapi
Version: 1.0.5
Summary: LangChain integration for AI Search API (LLM, Chat, tools, and chains).
Project-URL: Homepage, https://github.com/your-org/langchain-aisearchapi
Project-URL: Issues, https://github.com/your-org/langchain-aisearchapi/issues
Author: AI Search API Team
License: MIT License
License-File: LICENSE
Keywords: ai agents,ai chatbot,ai search api,aisearchapi,automation,chat models,contextual ai,contextual search,fact checking,intelligent agents,langchain,langchain-extension,langchain-integration,langchain-tools,large language models,llm,nlp,python ai,question answering,research chain,search api,semantic search,summarization api,summary api,web search api
Classifier: Development Status :: 4 - Beta
Classifier: Intended Audience :: Developers
Classifier: License :: OSI Approved :: MIT License
Classifier: Programming Language :: Python
Classifier: Programming Language :: Python :: 3
Classifier: Programming Language :: Python :: 3.9
Classifier: Programming Language :: Python :: 3.10
Classifier: Programming Language :: Python :: 3.11
Classifier: Programming Language :: Python :: 3.12
Classifier: Typing :: Typed
Requires-Python: >=3.9
Requires-Dist: aisearchapi-client>=0.1.0
Requires-Dist: langchain-core>=0.3.0
Requires-Dist: langchain>=0.2.14
Requires-Dist: pydantic>=2.6
Requires-Dist: requests>=2.28
Requires-Dist: typing-extensions>=4.8
